update_notifications/__init__.py
update_notifications/admin.py
update_notifications/apps.py
update_notifications/models.py
update_notifications/utils.py
update_notifications/views.py
update_notifications/migrations/0001_initial.py
update_notifications/migrations/__init__.py
django_update_notifications-0.1.5.dist-info/LICENSE
django_update_notifications-0.1.5.dist-info/METADATA
django_update_notifications-0.1.5.dist-info/WHEEL
django_update_notifications-0.1.5.dist-info/top_level.txt
django_update_notifications-0.1.5.dist-info/RECORD
